MANIFEST.in
README.rst
licence.txt
setup.py
VCSTodo.egg-info/PKG-INFO
VCSTodo.egg-info/SOURCES.txt
VCSTodo.egg-info/dependency_links.txt
VCSTodo.egg-info/top_level.txt
vcstodo/__init__.py
vcstodo/tdo
vcstodo/VCSTodo.egg-info/SOURCES.txt
vcstodo/VCSTodo.egg-info/dependency_links.txt
vcstodo/VCSTodo.egg-info/top_level.txt
vcstodo/libs/__init__.py
vcstodo/libs/clize.py
vcstodo/libs/config/__init__.py
vcstodo/libs/config/base.py