Metadata-Version: 1.0
Name: VCSTodo
Version: 0.1.1
Summary: Text based but human and VCS friendly task manager
Home-page: UNKNOWN
Author: Kevin Samuel
Author-email: kevin@yeleman.com
License: UNKNOWN
Platform: UNKNOWN
Classifier: Programming Language :: Python
Classifier: License :: OSI Approved :: GNU General Public License (GPL)
